setup.py
Landport.egg-info/PKG-INFO
Landport.egg-info/SOURCES.txt
Landport.egg-info/dependency_links.txt
Landport.egg-info/not-zip-safe
Landport.egg-info/requires.txt
Landport.egg-info/top_level.txt
landport/__init__.py
landport/core/__init__.py
landport/core/auth.py
landport/core/dispatch.py
landport/core/node.py
landport/core/rank.py
landport/core/sub.py
landport/core/user.py
landport/core/websocket.py
landport/utils/__init__.py
landport/utils/color.py
landport/utils/time_tools.py
landport/utils/ttl.py